gig/__init__.py
gig/core/Ent.py
gig/core/EntBase.py
gig/core/EntGIGMixin.py
gig/core/EntGeoMixin.py
gig/core/EntJSONMixin.py
gig/core/EntLoadMixin.py
gig/core/EntType.py
gig/core/GIGConstants.py
gig/core/GIGTable.py
gig/core/GIGTableRow.py
gig/core/__init__.py
gig_nuuuwan-4.0.0.dist-info/licenses/LICENSE
gig_nuuuwan-4.0.0.dist-info/METADATA
gig_nuuuwan-4.0.0.dist-info/WHEEL
gig_nuuuwan-4.0.0.dist-info/top_level.txt
gig_nuuuwan-4.0.0.dist-info/RECORD
